{
  "chunk_id": "race-001-fg-003-swing-voters-statewide-chunk-030",
  "focus_group_id": "race-001-fg-003-swing-voters-statewide",
  "content": "Traverse City tourism is doing okay but workers can't afford to live. Mixed. 2 out of 5.",
  "participant": "P3",
  "participant_profile": "F, 38, Retail manager, Traverse City, independent, tourism-dependent economy concerns",
  "section": "Message Testing Block 1: Economic Messages",
  "preceding_moderator_q": "Statement A: \"Michigan's economy is roaring back. Unemployment is at historic lows, new factories are opening, and our state is leading the nation in manufacturing growth.\"",
  "source_file": "political-consulting-corpus/races/race-001-michigan-gov-2022/focus-groups/fg-003-swing-voters-statewide.md",
  "line_number": 108
}