{
  "chunk_id": "race-001-fg-003-swing-voters-statewide-chunk-118",
  "focus_group_id": "race-001-fg-003-swing-voters-statewide",
  "content": "Talk about the root causes - economic opportunity, education, mental health. Crime doesn't happen in a vacuum.",
  "participant": "P4",
  "participant_profile": "M, 47, Auto plant worker (Stellantis), Sterling Heights, UAW member, Macomb County",
  "section": "Crime and Public Safety",
  "preceding_moderator_q": "What would an effective public safety message from Holloway look like?",
  "source_file": "political-consulting-corpus/races/race-001-michigan-gov-2022/focus-groups/fg-003-swing-voters-statewide.md",
  "line_number": 330
}