{
  "chunk_id": "race-008-fg-002-rural-ranching-chunk-052",
  "focus_group_id": "race-008-fg-002-rural-ranching",
  "content": "It's not about Jack. It's about sending a message. Democrats need to lose Montana completely.",
  "participant": "P3",
  "participant_profile": "M, 48, Wheat farmer, diversified operation, pragmatic politics",
  "section": "The Party Problem",
  "preceding_moderator_q": "Jack has voted against his party on many of these issues. Does that matter?",
  "source_file": "political-consulting-corpus/races/race-008-montana-senate-2024/focus-groups/fg-002-rural-ranching.md",
  "line_number": 162
}