{
  "chunk_id": "race-008-fg-002-rural-ranching-chunk-060",
  "focus_group_id": "race-008-fg-002-rural-ranching",
  "content": "It's empty but it lands. Sometimes you just want to vote against the other side.",
  "participant": "P3",
  "participant_profile": "M, 48, Wheat farmer, diversified operation, pragmatic politics",
  "section": "Personal vs. Partisan",
  "preceding_moderator_q": "Let me read some messages.",
  "source_file": "political-consulting-corpus/races/race-008-montana-senate-2024/focus-groups/fg-002-rural-ranching.md",
  "line_number": 188
}