{
  "chunk_id": "race-009-fg-003-grand-rapids-chunk-055",
  "focus_group_id": "race-009-fg-003-grand-rapids",
  "content": "I'm not a single-issue voter but his position is hard to defend.",
  "participant": "P9",
  "participant_profile": "M, 55, Auto supplier, Walker, industry concerns",
  "section": "Abortion's Impact in West Michigan",
  "preceding_moderator_q": "Does DeGroot's abortion position concern anyone who'd otherwise support him?",
  "source_file": "political-consulting-corpus/races/race-009-michigan-senate-2024/focus-groups/fg-003-grand-rapids.md",
  "line_number": 170
}