{
  "chunk_id": "race-007-fg-001-cleveland-suburbs-chunk-011",
  "focus_group_id": "race-007-fg-001-cleveland-suburbs",
  "content": "People feel less safe too. Not just crime but economic insecurity.",
  "participant": "P10",
  "participant_profile": "M, 45, Police officer, Strongsville, Trump 2020, law and order focus",
  "section": "Opening: Economic Anxiety in Cuyahoga County",
  "preceding_moderator_q": "How would you describe the trajectory?",
  "source_file": "political-consulting-corpus/races/race-007-ohio-senate-2024/focus-groups/fg-001-cleveland-suburbs.md",
  "line_number": 56
}