{
  "chunk_id": "race-005-fg-003-tucson-chunk-032",
  "focus_group_id": "race-005-fg-003-tucson",
  "content": "I literally moved here because I thought Arizona was getting better. She represents regression.",
  "participant": "P9",
  "participant_profile": "F, 31, Tech worker, remote, moved from Bay Area, reproductive rights focus",
  "section": "Kari Mitchell: Existential Threat",
  "preceding_moderator_q": "How do you view Kari Mitchell?",
  "source_file": "political-consulting-corpus/races/race-005-arizona-gov-2022/focus-groups/fg-003-tucson.md",
  "line_number": 114
}