{
  "chunk_id": "race-001-fg-001-detroit-suburbs-chunk-100",
  "focus_group_id": "race-001-fg-001-detroit-suburbs",
  "content": "Her dad at GM is good. Shows she understands manufacturing, working families.",
  "participant": "P1",
  "participant_profile": "F, 52, Small business owner (gift shop), Troy, independent, divorced, two adult children, voted split ticket 2020",
  "section": "Message Testing",
  "preceding_moderator_q": "Fourth statement: \"Sarah Holloway grew up right here in Oakland County. Her father worked at GM for thirty years. She went to public schools and put herself through college. She knows what it takes to build a good life in Michigan because she's lived it.\"",
  "source_file": "political-consulting-corpus/races/race-001-michigan-gov-2022/focus-groups/fg-001-detroit-suburbs.md",
  "line_number": 288
}