{
  "chunk_id": "race-005-fg-002-latino-phoenix-chunk-006",
  "focus_group_id": "race-005-fg-002-latino-phoenix",
  "content": "In construction, I work with everybody - white, Black, Latino. On the job site, we're just workers. Politics makes it weird.",
  "participant": "P2",
  "participant_profile": "M, 38, Construction foreman, Glendale, third-generation Mexican-American, union member",
  "section": "Opening: Latino Community in Arizona Today",
  "preceding_moderator_q": "Gracias por estar aqu\u00ed. Let's start in whatever language you're comfortable with. What's it like being Latino in Arizona right now?",
  "source_file": "political-consulting-corpus/races/race-005-arizona-gov-2022/focus-groups/fg-002-latino-phoenix.md",
  "line_number": 44
}