{
  "chunk_id": "race-009-fg-002-flint-saginaw-chunk-037",
  "focus_group_id": "race-009-fg-002-flint-saginaw",
  "content": "Rich guy who wants power. Seen it before.",
  "participant": "P8",
  "participant_profile": "F, 29, Healthcare aide, Flint, struggling economically",
  "section": "Mike DeGroot: Outsider",
  "preceding_moderator_q": "What about Mike DeGroot?",
  "source_file": "political-consulting-corpus/races/race-009-michigan-senate-2024/focus-groups/fg-002-flint-saginaw.md",
  "line_number": 122
}