{
  "chunk_id": "race-008-fg-001-billings-chunk-016",
  "focus_group_id": "race-008-fg-001-billings",
  "content": "Jack is Montana. Rancher, straight shooter, helps everyone regardless of party.",
  "participant": "P5",
  "participant_profile": "M, 67, Retired teacher, Billings, longtime Democrat, education focus",
  "section": "Senator Sullivan: The Personal Brand",
  "preceding_moderator_q": "Senator Jack Sullivan has been in office 18 years. What do you think of him?",
  "source_file": "political-consulting-corpus/races/race-008-montana-senate-2024/focus-groups/fg-001-billings.md",
  "line_number": 72
}